{
    "$schema": "http://json-schema.org/draft-04/schema#",
    "type": "object",
    "properties": {
      "githubURL": {
        "type": "string",
        "title": "GitHub repository",
        "description" : "Link to GitHub repository in proper format: repos/:owner/:repo or orgs/:org"
      },
      "workspaceName": {
        "type":"string",
        "title":"Workspace Name",
        "description": "The name of workspace application will be installed to."
      },
      "image": {
        "type":"string",
        "title":"Docker image",
        "description": "Docker image to install scenario from."
      }
    },
    "required":["githubURL","workspaceName"]
  }